README.md
setup.py
cloudmersive_configuration_api_client/__init__.py
cloudmersive_configuration_api_client/api_client.py
cloudmersive_configuration_api_client/configuration.py
cloudmersive_configuration_api_client/rest.py
cloudmersive_configuration_api_client.egg-info/PKG-INFO
cloudmersive_configuration_api_client.egg-info/SOURCES.txt
cloudmersive_configuration_api_client.egg-info/dependency_links.txt
cloudmersive_configuration_api_client.egg-info/requires.txt
cloudmersive_configuration_api_client.egg-info/top_level.txt
cloudmersive_configuration_api_client/api/__init__.py
cloudmersive_configuration_api_client/api/orchestrator_api.py
cloudmersive_configuration_api_client/api/settings_api.py
cloudmersive_configuration_api_client/models/__init__.py
cloudmersive_configuration_api_client/models/create_setting_request.py
cloudmersive_configuration_api_client/models/create_setting_response.py
cloudmersive_configuration_api_client/models/http_form_data_parameter.py
cloudmersive_configuration_api_client/models/http_get_parameter.py
cloudmersive_configuration_api_client/models/http_orchestration_header.py
cloudmersive_configuration_api_client/models/http_orchestration_request.py
cloudmersive_configuration_api_client/models/http_orchestration_response.py
cloudmersive_configuration_api_client/models/http_orchestration_task.py
cloudmersive_configuration_api_client/models/http_raw_binary_parameter.py
cloudmersive_configuration_api_client/models/http_raw_text_parameter.py
cloudmersive_configuration_api_client/models/http_www_form_url_encoded_parameter.py
cloudmersive_configuration_api_client/models/list_settings_request.py
cloudmersive_configuration_api_client/models/list_settings_response.py
cloudmersive_configuration_api_client/models/setting_value.py
cloudmersive_configuration_api_client/models/task_output_reference.py
cloudmersive_configuration_api_client/models/update_setting_request.py
cloudmersive_configuration_api_client/models/update_setting_response.py
test/__init__.py
test/test_create_setting_request.py
test/test_create_setting_response.py
test/test_http_form_data_parameter.py
test/test_http_get_parameter.py
test/test_http_orchestration_header.py
test/test_http_orchestration_request.py
test/test_http_orchestration_response.py
test/test_http_orchestration_task.py
