Metadata-Version: 2.1
Name: cloudmersive-configuration-api-client
Version: 2.4.1
Summary: configapi
Home-page: https://www.cloudmersive.com/
Author-email: 
License: UNKNOWN
Keywords: Swagger,configapi
Platform: UNKNOWN
